LICENSE
README.md
setup.py
alnlp/__init__.py
alnlp/version.py
alnlp/algorithms/__init__.py
alnlp/algorithms/chu_liu_edmonds.py
alnlp/common/__init__.py
alnlp/common/checks.py
alnlp/common/from_params.py
alnlp/common/lazy.py
alnlp/common/params.py
alnlp/common/registrable.py
alnlp/data/__init__.py
alnlp/data/ontonotes.py
alnlp/data/util.py
alnlp/metrics/__init__.py
alnlp/metrics/attachment_scores.py
alnlp/metrics/auc.py
alnlp/metrics/average.py
alnlp/metrics/bleu.py
alnlp/metrics/boolean_accuracy.py
alnlp/metrics/categorical_accuracy.py
alnlp/metrics/conll_coref_scores.py
alnlp/metrics/covariance.py
alnlp/metrics/entropy.py
alnlp/metrics/evalb_bracketing_scorer.py
alnlp/metrics/f1_measure.py
alnlp/metrics/fbeta_measure.py
alnlp/metrics/mean_absolute_error.py
alnlp/metrics/mention_recall.py
alnlp/metrics/metric.py
alnlp/metrics/pearson_correlation.py
alnlp/metrics/perplexity.py
alnlp/metrics/rouge.py
alnlp/metrics/sequence_accuracy.py
alnlp/metrics/span_based_f1_measure.py
alnlp/metrics/span_utils.py
alnlp/metrics/spearman_correlation.py
alnlp/metrics/unigram_recall.py
alnlp/models/__init__.py
alnlp/models/coref.py
alnlp/models/ontonotes.py
alnlp/models/util.py
alnlp/modules/__init__.py
alnlp/modules/augmented_lstm.py
alnlp/modules/cnn_encoder.py
alnlp/modules/conditional_random_field.py
alnlp/modules/encoder_base.py
alnlp/modules/endpoint_span_extractor.py
alnlp/modules/feedforward.py
alnlp/modules/gated_sum.py
alnlp/modules/initializers.py
alnlp/modules/input_variational_dropout.py
alnlp/modules/pass_through_encoder.py
alnlp/modules/pytorch_seq2seq_wrapper.py
alnlp/modules/self_attentive_span_extractor.py
alnlp/modules/seq2seq_encoder.py
alnlp/modules/span_extractor.py
alnlp/modules/stacked_alternating_lstm.py
alnlp/modules/stacked_bidirectional_lstm.py
alnlp/modules/time_distributed.py
alnlp/modules/util.py
alnlp/training/__init__.py
alnlp/training/optimizers.py