Metadata-Version: 2.1
Name: alnlp
Version: 1.0.0rc25
Summary: NLP metrics.
Home-page: https://github.com/allenai/allennlp
License: Apache
Keywords: nlp metrics
Platform: UNKNOWN
Classifier: Intended Audience :: Science/Research
Classifier: Development Status :: 3 - Alpha
Classifier: License :: OSI Approved :: Apache Software License
Classifier: Programming Language :: Python :: 3.6
Classifier: Topic :: Scientific/Engineering :: Artificial Intelligence
Requires-Python: >=3.6
